trains_agent/__init__.py
trains_agent/__main__.py
trains_agent/complete.py
trains_agent/config.py
trains_agent/definitions.py
trains_agent/errors.py
trains_agent/session.py
trains_agent/version.py
trains_agent/backend_api/__init__.py
trains_agent/backend_api/utils.py
trains_agent/backend_api/config/__init__.py
trains_agent/backend_api/config/default/agent.conf
trains_agent/backend_api/config/default/api.conf
trains_agent/backend_api/config/default/logging.conf
trains_agent/backend_api/config/default/sdk.conf
trains_agent/backend_api/schema/__init__.py
trains_agent/backend_api/schema/action.py
trains_agent/backend_api/schema/service.py
trains_agent/backend_api/services/__init__.py
trains_agent/backend_api/services/v2_4/__init__.py
trains_agent/backend_api/services/v2_4/auth.py
trains_agent/backend_api/services/v2_4/debug.py
trains_agent/backend_api/services/v2_4/events.py
trains_agent/backend_api/services/v2_4/models.py
trains_agent/backend_api/services/v2_4/queues.py
trains_agent/backend_api/services/v2_4/tasks.py
trains_agent/backend_api/services/v2_4/workers.py
trains_agent/backend_api/services/v2_5/__init__.py
trains_agent/backend_api/services/v2_5/auth.py
trains_agent/backend_api/services/v2_5/debug.py
trains_agent/backend_api/services/v2_5/events.py
trains_agent/backend_api/services/v2_5/models.py
trains_agent/backend_api/services/v2_5/queues.py
trains_agent/backend_api/services/v2_5/tasks.py
trains_agent/backend_api/services/v2_5/workers.py
trains_agent/backend_api/session/__init__.py
trains_agent/backend_api/session/apimodel.py
trains_agent/backend_api/session/callresult.py
trains_agent/backend_api/session/datamodel.py
trains_agent/backend_api/session/defs.py
trains_agent/backend_api/session/errors.py
trains_agent/backend_api/session/request.py
trains_agent/backend_api/session/response.py
trains_agent/backend_api/session/session.py
trains_agent/backend_api/session/token_manager.py
trains_agent/backend_api/session/client/__init__.py
trains_agent-0.16.3.dist-info/LICENSE
trains_agent-0.16.3.dist-info/METADATA
trains_agent-0.16.3.dist-info/WHEEL
trains_agent-0.16.3.dist-info/entry_points.txt
trains_agent-0.16.3.dist-info/top_level.txt
trains_agent-0.16.3.dist-info/RECORD
