Metadata-Version: 2.1
Name: trains-agent
Version: 0.16.3
Summary: TRAINS Agent - Auto-Magical DevOps for Deep Learning
Home-page: https://github.com/allegroai/trains-agent
Author: Allegroai
Author-email: trains@allegro.ai
License: Apache License 2.0
Keywords: trains devops machine deep learning agent automation hpc cluster
Platform: UNKNOWN
Classifier: Development Status :: 4 - Beta
Classifier: Intended Audience :: Developers
Classifier: Intended Audience :: System Administrators
Classifier: Intended Audience :: Science/Research
Classifier: Operating System :: POSIX :: Linux
Classifier: Operating System :: MacOS :: MacOS X
Classifier: Operating System :: Microsoft
Classifier: Topic :: Scientific/Engineering :: Artificial Intelligence
Classifier: Topic :: Scientific/Engineering :: Image Recognition
Classifier: Topic :: System :: Logging
Classifier: Topic :: System :: Monitoring
Classifier: Programming Language :: Python :: 3.5
Classifier: Programming Language :: Python :: 3.6
Classifier: Programming Language :: Python :: 3.7
Classifier: License :: OSI Approved :: Apache Software License
Requires-Dist: attrs (<20.4.0,>=18.0)
Requires-Dist: furl (<2.2.0,>=2.0.0)
Requires-Dist: future (<0.19.0,>=0.16.0)
Requires-Dist: humanfriendly (<9.2,>=2.1)
Requires-Dist: jsonschema (<3.3.0,>=2.6.0)
Requires-Dist: pathlib2 (<2.4.0,>=2.3.0)
Requires-Dist: psutil (<5.9.0,>=3.4.2)
Requires-Dist: pyhocon (<0.4.0,>=0.3.38)
Requires-Dist: pyparsing (<2.5.0,>=2.0.3)
Requires-Dist: python-dateutil (<2.9.0,>=2.4.2)
Requires-Dist: pyjwt (<2.0.0,>=1.6.4)
Requires-Dist: PyYAML (<5.4.0,>=3.12)
Requires-Dist: requests-file (<1.6.0,>=1.4.2)
Requires-Dist: requests (<2.26.0,>=2.20.0)
Requires-Dist: six (<1.16.0,>=1.11.0)
Requires-Dist: tqdm (<4.55.0,>=4.19.5)
Requires-Dist: typing (<3.8.0,>=3.6.4)
Requires-Dist: urllib3 (<1.27.0,>=1.21.1)
Requires-Dist: virtualenv (<20,>=16)
Requires-Dist: enum34 (<1.2.0,>=0.9) ; python_version < "3.6"
